{
  "xMin": 30,
  "xMax": 150,
  "yMin": 65,
  "yMax": 135,
  "xReverse": 0,
  "yReverse": 1,
  "presets": [
    {
      "id": "center",
      "label": "回中",
      "desc": "绝对 (90, 90)",
      "steps": [
        {
          "x": 90,
          "y": 90,
          "xm": 0,
          "ym": 0,
          "ms": 400
        }
      ]
    },
    {
      "id": "look_left",
      "label": "左看",
      "desc": "绝对 x=30",
      "steps": [
        {
          "x": 30,
          "y": 90,
          "xm": 0,
          "ym": 0,
          "ms": 500
        }
      ]
    },
    {
      "id": "look_right",
      "label": "右看",
      "desc": "绝对 x=150",
      "steps": [
        {
          "x": 150,
          "y": 90,
          "xm": 0,
          "ym": 0,
          "ms": 500
        }
      ]
    },
    {
      "id": "look_up",
      "label": "上看",
      "desc": "绝对 y=135",
      "steps": [
        {
          "x": 90,
          "y": 135,
          "xm": 0,
          "ym": 0,
          "ms": 500
        }
      ]
    },
    {
      "id": "look_down",
      "label": "下看",
      "desc": "绝对 y=65",
      "steps": [
        {
          "x": 90,
          "y": 65,
          "xm": 0,
          "ym": 0,
          "ms": 500
        }
      ]
    },
    {
      "id": "look_upper_left",
      "label": "左上看",
      "desc": "绝对 (30, 135)",
      "steps": [
        {
          "x": 30,
          "y": 135,
          "xm": 0,
          "ym": 0,
          "ms": 500
        }
      ]
    },
    {
      "id": "look_upper_right",
      "label": "右上看",
      "desc": "绝对 (150, 135)",
      "steps": [
        {
          "x": 150,
          "y": 135,
          "xm": 0,
          "ym": 0,
          "ms": 500
        }
      ]
    },
    {
      "id": "look_lower_left",
      "label": "左下看",
      "desc": "绝对 (30, 65)",
      "steps": [
        {
          "x": 30,
          "y": 65,
          "xm": 0,
          "ym": 0,
          "ms": 500
        }
      ]
    },
    {
      "id": "look_lower_right",
      "label": "右下看",
      "desc": "绝对 (150, 65)",
      "steps": [
        {
          "x": 150,
          "y": 65,
          "xm": 0,
          "ym": 0,
          "ms": 500
        }
      ]
    },
    {
      "id": "shake_head",
      "label": "摇头",
      "desc": "左→右→回中（相对 3 步）",
      "steps": [
        {
          "x": -18,
          "y": 0,
          "xm": 1,
          "ym": 1,
          "ms": 420
        },
        {
          "x": 36,
          "y": 0,
          "xm": 1,
          "ym": 1,
          "ms": 440
        },
        {
          "x": -18,
          "y": 0,
          "xm": 1,
          "ym": 1,
          "ms": 420
        }
      ]
    },
    {
      "id": "nod_head",
      "label": "点头",
      "desc": "下→上→回中（相对 3 步）",
      "steps": [
        {
          "x": 0,
          "y": -15,
          "xm": 1,
          "ym": 1,
          "ms": 350
        },
        {
          "x": 0,
          "y": 30,
          "xm": 1,
          "ym": 1,
          "ms": 380
        },
        {
          "x": 0,
          "y": -15,
          "xm": 1,
          "ym": 1,
          "ms": 350
        }
      ]
    }
  ]
}
